{
	"associated_units": [
		"11146:bb"
	],
	"attackInfo": [
		{
			"hits": 11,
			"id": "1",
			"target": "AOE"
		}
	],
	"bfmtMetadata": {
		"createdAt": "2017-09-15T11:31:46.000Z",
		"updatedAt": "2017-11-15T11:13:03.000Z"
	},
	"damage frames": [
		{
			"effect delay time(ms)/frame": "33.3/2",
			"frame times": [
				12,
				15,
				18,
				21,
				24,
				70,
				73,
				76,
				79,
				82,
				85
			],
			"hit dmg% distribution": [
				14,
				12,
				8,
				6,
				4,
				16,
				12,
				10,
				8,
				6,
				4
			],
			"hit dmg% distribution (total)": 100,
			"hits": 11,
			"proc id": "1"
		},
		{
			"effect delay time(ms)/frame": "0.0/0",
			"frame times": [
				0
			],
			"hit dmg% distribution": [
				100
			],
			"hit dmg% distribution (total)": 100,
			"hits": 1,
			"proc id": "5"
		},
		{
			"effect delay time(ms)/frame": "0.0/0",
			"frame times": [
				0
			],
			"hit dmg% distribution": [
				100
			],
			"hit dmg% distribution (total)": 100,
			"hits": 1,
			"proc id": "24"
		},
		{
			"effect delay time(ms)/frame": "16.7/1",
			"frame times": [
				0
			],
			"hit dmg% distribution": [
				100
			],
			"hit dmg% distribution (total)": 100,
			"hits": 1,
			"proc id": "24"
		},
		{
			"effect delay time(ms)/frame": "0.0/0",
			"frame times": [
				0
			],
			"hit dmg% distribution": [
				100
			],
			"hit dmg% distribution (total)": 100,
			"hits": 1,
			"proc id": "126"
		}
	],
	"desc": "11 combo Fire attack on all foes, hugely boosts Atk, Def for 3 turns, hugely boosts Atk relative to Def for 3 turns, hugely boosts Def relative to Atk for 3 turns & slight additional damage reduction for 2 turns",
	"drop check count": 1,
	"id": "11146",
	"levels": [
		{
			"bc cost": 21,
			"effects": [
				{
					"bb atk%": 280,
					"bb flat atk": 100,
					"effect delay time(ms)/frame": "33.3/2",
					"params": "280,100,0,0,0,0",
					"proc id": "1",
					"target area": "aoe",
					"target type": "enemy"
				},
				{
					"atk% buff (1)": 110,
					"buff turns": 3,
					"def% buff (3)": 110,
					"effect delay time(ms)/frame": "0.0/0",
					"element buffed": "all",
					"params": "0,110,110,0,0,3,135",
					"proc id": "5",
					"target area": "aoe",
					"target type": "party"
				},
				{
					"% converted turns": 3,
					"converted attribute": "attack",
					"def% buff (47)": 50,
					"effect delay time(ms)/frame": "0.0/0",
					"params": "1,0,50,0,3,135",
					"proc id": "24",
					"target area": "aoe",
					"target type": "party"
				},
				{
					"% converted turns": 3,
					"atk% buff (46)": 50,
					"converted attribute": "defense",
					"effect delay time(ms)/frame": "16.7/1",
					"params": "2,50,0,0,3,135",
					"proc id": "24",
					"target area": "aoe",
					"target type": "party"
				},
				{
					"effect delay time(ms)/frame": "0.0/0",
					"params": "10,2,135",
					"proc id": "126",
					"target area": "aoe",
					"target type": "party"
				}
			]
		},
		{
			"bc cost": 21,
			"effects": [
				{
					"bb atk%": 290,
					"bb flat atk": 100,
					"effect delay time(ms)/frame": "33.3/2",
					"params": "290,100,0,0,0,0",
					"proc id": "1",
					"target area": "aoe",
					"target type": "enemy"
				},
				{
					"atk% buff (1)": 115,
					"buff turns": 3,
					"def% buff (3)": 115,
					"effect delay time(ms)/frame": "0.0/0",
					"element buffed": "all",
					"params": "0,115,115,0,0,3,135",
					"proc id": "5",
					"target area": "aoe",
					"target type": "party"
				},
				{
					"% converted turns": 3,
					"converted attribute": "attack",
					"def% buff (47)": 52,
					"effect delay time(ms)/frame": "0.0/0",
					"params": "1,0,52,0,3,135",
					"proc id": "24",
					"target area": "aoe",
					"target type": "party"
				},
				{
					"% converted turns": 3,
					"atk% buff (46)": 52,
					"converted attribute": "defense",
					"effect delay time(ms)/frame": "16.7/1",
					"params": "2,52,0,0,3,135",
					"proc id": "24",
					"target area": "aoe",
					"target type": "party"
				},
				{
					"effect delay time(ms)/frame": "0.0/0",
					"params": "10,2,135",
					"proc id": "126",
					"target area": "aoe",
					"target type": "party"
				}
			]
		},
		{
			"bc cost": 21,
			"effects": [
				{
					"bb atk%": 300,
					"bb flat atk": 100,
					"effect delay time(ms)/frame": "33.3/2",
					"params": "300,100,0,0,0,0",
					"proc id": "1",
					"target area": "aoe",
					"target type": "enemy"
				},
				{
					"atk% buff (1)": 120,
					"buff turns": 3,
					"def% buff (3)": 120,
					"effect delay time(ms)/frame": "0.0/0",
					"element buffed": "all",
					"params": "0,120,120,0,0,3,135",
					"proc id": "5",
					"target area": "aoe",
					"target type": "party"
				},
				{
					"% converted turns": 3,
					"converted attribute": "attack",
					"def% buff (47)": 54,
					"effect delay time(ms)/frame": "0.0/0",
					"params": "1,0,54,0,3,135",
					"proc id": "24",
					"target area": "aoe",
					"target type": "party"
				},
				{
					"% converted turns": 3,
					"atk% buff (46)": 54,
					"converted attribute": "defense",
					"effect delay time(ms)/frame": "16.7/1",
					"params": "2,54,0,0,3,135",
					"proc id": "24",
					"target area": "aoe",
					"target type": "party"
				},
				{
					"effect delay time(ms)/frame": "0.0/0",
					"params": "10,2,135",
					"proc id": "126",
					"target area": "aoe",
					"target type": "party"
				}
			]
		},
		{
			"bc cost": 21,
			"effects": [
				{
					"bb atk%": 310,
					"bb flat atk": 100,
					"effect delay time(ms)/frame": "33.3/2",
					"params": "310,100,0,0,0,0",
					"proc id": "1",
					"target area": "aoe",
					"target type": "enemy"
				},
				{
					"atk% buff (1)": 125,
					"buff turns": 3,
					"def% buff (3)": 125,
					"effect delay time(ms)/frame": "0.0/0",
					"element buffed": "all",
					"params": "0,125,125,0,0,3,135",
					"proc id": "5",
					"target area": "aoe",
					"target type": "party"
				},
				{
					"% converted turns": 3,
					"converted attribute": "attack",
					"def% buff (47)": 56,
					"effect delay time(ms)/frame": "0.0/0",
					"params": "1,0,56,0,3,135",
					"proc id": "24",
					"target area": "aoe",
					"target type": "party"
				},
				{
					"% converted turns": 3,
					"atk% buff (46)": 56,
					"converted attribute": "defense",
					"effect delay time(ms)/frame": "16.7/1",
					"params": "2,56,0,0,3,135",
					"proc id": "24",
					"target area": "aoe",
					"target type": "party"
				},
				{
					"effect delay time(ms)/frame": "0.0/0",
					"params": "10,2,135",
					"proc id": "126",
					"target area": "aoe",
					"target type": "party"
				}
			]
		},
		{
			"bc cost": 21,
			"effects": [
				{
					"bb atk%": 320,
					"bb flat atk": 100,
					"effect delay time(ms)/frame": "33.3/2",
					"params": "320,100,0,0,0,0",
					"proc id": "1",
					"target area": "aoe",
					"target type": "enemy"
				},
				{
					"atk% buff (1)": 130,
					"buff turns": 3,
					"def% buff (3)": 130,
					"effect delay time(ms)/frame": "0.0/0",
					"element buffed": "all",
					"params": "0,130,130,0,0,3,135",
					"proc id": "5",
					"target area": "aoe",
					"target type": "party"
				},
				{
					"% converted turns": 3,
					"converted attribute": "attack",
					"def% buff (47)": 58,
					"effect delay time(ms)/frame": "0.0/0",
					"params": "1,0,58,0,3,135",
					"proc id": "24",
					"target area": "aoe",
					"target type": "party"
				},
				{
					"% converted turns": 3,
					"atk% buff (46)": 58,
					"converted attribute": "defense",
					"effect delay time(ms)/frame": "16.7/1",
					"params": "2,58,0,0,3,135",
					"proc id": "24",
					"target area": "aoe",
					"target type": "party"
				},
				{
					"effect delay time(ms)/frame": "0.0/0",
					"params": "10,2,135",
					"proc id": "126",
					"target area": "aoe",
					"target type": "party"
				}
			]
		},
		{
			"bc cost": 21,
			"effects": [
				{
					"bb atk%": 330,
					"bb flat atk": 100,
					"effect delay time(ms)/frame": "33.3/2",
					"params": "330,100,0,0,0,0",
					"proc id": "1",
					"target area": "aoe",
					"target type": "enemy"
				},
				{
					"atk% buff (1)": 135,
					"buff turns": 3,
					"def% buff (3)": 135,
					"effect delay time(ms)/frame": "0.0/0",
					"element buffed": "all",
					"params": "0,135,135,0,0,3,135",
					"proc id": "5",
					"target area": "aoe",
					"target type": "party"
				},
				{
					"% converted turns": 3,
					"converted attribute": "attack",
					"def% buff (47)": 60,
					"effect delay time(ms)/frame": "0.0/0",
					"params": "1,0,60,0,3,135",
					"proc id": "24",
					"target area": "aoe",
					"target type": "party"
				},
				{
					"% converted turns": 3,
					"atk% buff (46)": 60,
					"converted attribute": "defense",
					"effect delay time(ms)/frame": "16.7/1",
					"params": "2,60,0,0,3,135",
					"proc id": "24",
					"target area": "aoe",
					"target type": "party"
				},
				{
					"effect delay time(ms)/frame": "0.0/0",
					"params": "10,2,135",
					"proc id": "126",
					"target area": "aoe",
					"target type": "party"
				}
			]
		},
		{
			"bc cost": 21,
			"effects": [
				{
					"bb atk%": 340,
					"bb flat atk": 100,
					"effect delay time(ms)/frame": "33.3/2",
					"params": "340,100,0,0,0,0",
					"proc id": "1",
					"target area": "aoe",
					"target type": "enemy"
				},
				{
					"atk% buff (1)": 140,
					"buff turns": 3,
					"def% buff (3)": 140,
					"effect delay time(ms)/frame": "0.0/0",
					"element buffed": "all",
					"params": "0,140,140,0,0,3,135",
					"proc id": "5",
					"target area": "aoe",
					"target type": "party"
				},
				{
					"% converted turns": 3,
					"converted attribute": "attack",
					"def% buff (47)": 62,
					"effect delay time(ms)/frame": "0.0/0",
					"params": "1,0,62,0,3,135",
					"proc id": "24",
					"target area": "aoe",
					"target type": "party"
				},
				{
					"% converted turns": 3,
					"atk% buff (46)": 62,
					"converted attribute": "defense",
					"effect delay time(ms)/frame": "16.7/1",
					"params": "2,62,0,0,3,135",
					"proc id": "24",
					"target area": "aoe",
					"target type": "party"
				},
				{
					"effect delay time(ms)/frame": "0.0/0",
					"params": "10,2,135",
					"proc id": "126",
					"target area": "aoe",
					"target type": "party"
				}
			]
		},
		{
			"bc cost": 21,
			"effects": [
				{
					"bb atk%": 350,
					"bb flat atk": 100,
					"effect delay time(ms)/frame": "33.3/2",
					"params": "350,100,0,0,0,0",
					"proc id": "1",
					"target area": "aoe",
					"target type": "enemy"
				},
				{
					"atk% buff (1)": 145,
					"buff turns": 3,
					"def% buff (3)": 145,
					"effect delay time(ms)/frame": "0.0/0",
					"element buffed": "all",
					"params": "0,145,145,0,0,3,135",
					"proc id": "5",
					"target area": "aoe",
					"target type": "party"
				},
				{
					"% converted turns": 3,
					"converted attribute": "attack",
					"def% buff (47)": 64,
					"effect delay time(ms)/frame": "0.0/0",
					"params": "1,0,64,0,3,135",
					"proc id": "24",
					"target area": "aoe",
					"target type": "party"
				},
				{
					"% converted turns": 3,
					"atk% buff (46)": 64,
					"converted attribute": "defense",
					"effect delay time(ms)/frame": "16.7/1",
					"params": "2,64,0,0,3,135",
					"proc id": "24",
					"target area": "aoe",
					"target type": "party"
				},
				{
					"effect delay time(ms)/frame": "0.0/0",
					"params": "10,2,135",
					"proc id": "126",
					"target area": "aoe",
					"target type": "party"
				}
			]
		},
		{
			"bc cost": 21,
			"effects": [
				{
					"bb atk%": 360,
					"bb flat atk": 100,
					"effect delay time(ms)/frame": "33.3/2",
					"params": "360,100,0,0,0,0",
					"proc id": "1",
					"target area": "aoe",
					"target type": "enemy"
				},
				{
					"atk% buff (1)": 150,
					"buff turns": 3,
					"def% buff (3)": 150,
					"effect delay time(ms)/frame": "0.0/0",
					"element buffed": "all",
					"params": "0,150,150,0,0,3,135",
					"proc id": "5",
					"target area": "aoe",
					"target type": "party"
				},
				{
					"% converted turns": 3,
					"converted attribute": "attack",
					"def% buff (47)": 66,
					"effect delay time(ms)/frame": "0.0/0",
					"params": "1,0,66,0,3,135",
					"proc id": "24",
					"target area": "aoe",
					"target type": "party"
				},
				{
					"% converted turns": 3,
					"atk% buff (46)": 66,
					"converted attribute": "defense",
					"effect delay time(ms)/frame": "16.7/1",
					"params": "2,66,0,0,3,135",
					"proc id": "24",
					"target area": "aoe",
					"target type": "party"
				},
				{
					"effect delay time(ms)/frame": "0.0/0",
					"params": "10,2,135",
					"proc id": "126",
					"target area": "aoe",
					"target type": "party"
				}
			]
		},
		{
			"bc cost": 21,
			"effects": [
				{
					"bb atk%": 380,
					"bb flat atk": 100,
					"effect delay time(ms)/frame": "33.3/2",
					"params": "380,100,0,0,0,0",
					"proc id": "1",
					"target area": "aoe",
					"target type": "enemy"
				},
				{
					"atk% buff (1)": 160,
					"buff turns": 3,
					"def% buff (3)": 160,
					"effect delay time(ms)/frame": "0.0/0",
					"element buffed": "all",
					"params": "0,160,160,0,0,3,135",
					"proc id": "5",
					"target area": "aoe",
					"target type": "party"
				},
				{
					"% converted turns": 3,
					"converted attribute": "attack",
					"def% buff (47)": 70,
					"effect delay time(ms)/frame": "0.0/0",
					"params": "1,0,70,0,3,135",
					"proc id": "24",
					"target area": "aoe",
					"target type": "party"
				},
				{
					"% converted turns": 3,
					"atk% buff (46)": 70,
					"converted attribute": "defense",
					"effect delay time(ms)/frame": "16.7/1",
					"params": "2,70,0,0,3,135",
					"proc id": "24",
					"target area": "aoe",
					"target type": "party"
				},
				{
					"effect delay time(ms)/frame": "0.0/0",
					"params": "10,2,135",
					"proc id": "126",
					"target area": "aoe",
					"target type": "party"
				}
			]
		}
	],
	"name": "Dragon Tempest"
}