{
	"associated_units": [
		"840658:sbb"
	],
	"attackInfo": [
		{
			"hits": 19,
			"id": "47",
			"target": "AOE"
		},
		{
			"hits": 3,
			"id": "1",
			"target": "ST"
		}
	],
	"bfmtMetadata": {
		"createdAt": "2017-09-15T11:31:46.000Z",
		"updatedAt": "2019-02-08T04:00:05.000Z"
	},
	"damage frames": [
		{
			"effect delay time(ms)/frame": "16.7/1",
			"frame times": [
				69,
				72,
				75,
				87,
				90,
				93,
				96,
				99,
				102,
				105,
				108,
				111,
				114,
				117,
				120,
				123,
				126,
				129,
				132
			],
			"hit dmg% distribution": [
				4,
				4,
				4,
				4,
				4,
				6,
				6,
				6,
				6,
				6,
				6,
				6,
				6,
				6,
				6,
				6,
				6,
				4,
				4
			],
			"hit dmg% distribution (total)": 100,
			"hits": 19,
			"proc id": "47"
		},
		{
			"effect delay time(ms)/frame": "16.7/1",
			"frame times": [
				109,
				112,
				115
			],
			"hit dmg% distribution": [
				33,
				33,
				34
			],
			"hit dmg% distribution (total)": 100,
			"hits": 3,
			"proc id": "1"
		},
		{
			"effect delay time(ms)/frame": "0.0/0",
			"frame times": [
				0
			],
			"hit dmg% distribution": [
				100
			],
			"hit dmg% distribution (total)": 100,
			"hits": 1,
			"proc id": "45"
		},
		{
			"effect delay time(ms)/frame": "0.0/0",
			"frame times": [
				0
			],
			"hit dmg% distribution": [
				100
			],
			"hit dmg% distribution (total)": 100,
			"hits": 1,
			"proc id": "24"
		},
		{
			"effect delay time(ms)/frame": "0.0/0",
			"frame times": [
				0
			],
			"hit dmg% distribution": [
				100
			],
			"hit dmg% distribution (total)": 100,
			"hits": 1,
			"proc id": "9"
		},
		{
			"effect delay time(ms)/frame": "0.0/0",
			"frame times": [
				0
			],
			"hit dmg% distribution": [
				100
			],
			"hit dmg% distribution (total)": 100,
			"hits": 1,
			"proc id": "54"
		}
	],
	"desc": "19 combo massive Thunder attack on all foes (damage relative to remaining HP), 3 combo massive Thunder attack on single foe, enormously boosts BB Atk for 3 turns, hugely boosts Atk, Def relative to Rec for 3 turns, probable 2 turn Atk, Def reduction & greatly boosts critical damage for 3 turns",
	"drop check count": 1,
	"id": "1840658",
	"levels": [
		{
			"bc cost": 28,
			"effects": [
				{
					"bb added atk% based on hp": 900,
					"bb added atk% proportional to hp": "remaining",
					"bb base atk%": 200,
					"bb flat atk": 200,
					"effect delay time(ms)/frame": "16.7/1",
					"params": "200,1100,0,200,0,0,0,0",
					"proc id": "47",
					"target area": "aoe",
					"target type": "enemy"
				},
				{
					"bb atk%": 1100,
					"bb flat atk": 200,
					"effect delay time(ms)/frame": "16.7/1",
					"params": "1100,200,0,0,0,0",
					"proc id": "1",
					"target area": "single",
					"target type": "enemy"
				},
				{
					"bb atk% buff": 500,
					"buff turns (72)": 3,
					"effect delay time(ms)/frame": "0.0/0",
					"params": "500,500,500,3,0",
					"proc id": "45",
					"sbb atk% buff": 500,
					"target area": "aoe",
					"target type": "party",
					"ubb atk% buff": 500
				},
				{
					"% converted turns": 3,
					"atk% buff (46)": 110,
					"converted attribute": "recovery",
					"def% buff (47)": 110,
					"effect delay time(ms)/frame": "0.0/0",
					"params": "3,110,110,0,3,0",
					"proc id": "24",
					"target area": "aoe",
					"target type": "party"
				},
				{
					"buff #1": {
						"atk% buff (2)": -60,
						"proc chance%": 40
					},
					"buff #2": {
						"def% buff (4)": -60,
						"proc chance%": 40
					},
					"buff turns": 2,
					"effect delay time(ms)/frame": "0.0/0",
					"element buffed": "all",
					"params": "0,1,-60,40,2,-60,40,2,0",
					"proc id": "9",
					"target area": "aoe",
					"target type": "enemy"
				},
				{
					"buff turns (84)": 3,
					"crit multiplier%": 125,
					"effect delay time(ms)/frame": "0.0/0",
					"params": "1.25,3,0",
					"proc id": "54",
					"target area": "aoe",
					"target type": "party"
				}
			]
		},
		{
			"bc cost": 28,
			"effects": [
				{
					"bb added atk% based on hp": 910,
					"bb added atk% proportional to hp": "remaining",
					"bb base atk%": 200,
					"bb flat atk": 200,
					"effect delay time(ms)/frame": "16.7/1",
					"params": "200,1110,0,200,0,0,0,0",
					"proc id": "47",
					"target area": "aoe",
					"target type": "enemy"
				},
				{
					"bb atk%": 1110,
					"bb flat atk": 200,
					"effect delay time(ms)/frame": "16.7/1",
					"params": "1110,200,0,0,0,0",
					"proc id": "1",
					"target area": "single",
					"target type": "enemy"
				},
				{
					"bb atk% buff": 510,
					"buff turns (72)": 3,
					"effect delay time(ms)/frame": "0.0/0",
					"params": "510,510,510,3,0",
					"proc id": "45",
					"sbb atk% buff": 510,
					"target area": "aoe",
					"target type": "party",
					"ubb atk% buff": 510
				},
				{
					"% converted turns": 3,
					"atk% buff (46)": 110,
					"converted attribute": "recovery",
					"def% buff (47)": 110,
					"effect delay time(ms)/frame": "0.0/0",
					"params": "3,110,110,0,3,0",
					"proc id": "24",
					"target area": "aoe",
					"target type": "party"
				},
				{
					"buff #1": {
						"atk% buff (2)": -60,
						"proc chance%": 40
					},
					"buff #2": {
						"def% buff (4)": -60,
						"proc chance%": 40
					},
					"buff turns": 2,
					"effect delay time(ms)/frame": "0.0/0",
					"element buffed": "all",
					"params": "0,1,-60,40,2,-60,40,2,0",
					"proc id": "9",
					"target area": "aoe",
					"target type": "enemy"
				},
				{
					"buff turns (84)": 3,
					"crit multiplier%": 125,
					"effect delay time(ms)/frame": "0.0/0",
					"params": "1.25,3,0",
					"proc id": "54",
					"target area": "aoe",
					"target type": "party"
				}
			]
		},
		{
			"bc cost": 28,
			"effects": [
				{
					"bb added atk% based on hp": 920,
					"bb added atk% proportional to hp": "remaining",
					"bb base atk%": 200,
					"bb flat atk": 200,
					"effect delay time(ms)/frame": "16.7/1",
					"params": "200,1120,0,200,0,0,0,0",
					"proc id": "47",
					"target area": "aoe",
					"target type": "enemy"
				},
				{
					"bb atk%": 1120,
					"bb flat atk": 200,
					"effect delay time(ms)/frame": "16.7/1",
					"params": "1120,200,0,0,0,0",
					"proc id": "1",
					"target area": "single",
					"target type": "enemy"
				},
				{
					"bb atk% buff": 520,
					"buff turns (72)": 3,
					"effect delay time(ms)/frame": "0.0/0",
					"params": "520,520,520,3,0",
					"proc id": "45",
					"sbb atk% buff": 520,
					"target area": "aoe",
					"target type": "party",
					"ubb atk% buff": 520
				},
				{
					"% converted turns": 3,
					"atk% buff (46)": 110,
					"converted attribute": "recovery",
					"def% buff (47)": 110,
					"effect delay time(ms)/frame": "0.0/0",
					"params": "3,110,110,0,3,0",
					"proc id": "24",
					"target area": "aoe",
					"target type": "party"
				},
				{
					"buff #1": {
						"atk% buff (2)": -60,
						"proc chance%": 40
					},
					"buff #2": {
						"def% buff (4)": -60,
						"proc chance%": 40
					},
					"buff turns": 2,
					"effect delay time(ms)/frame": "0.0/0",
					"element buffed": "all",
					"params": "0,1,-60,40,2,-60,40,2,0",
					"proc id": "9",
					"target area": "aoe",
					"target type": "enemy"
				},
				{
					"buff turns (84)": 3,
					"crit multiplier%": 125,
					"effect delay time(ms)/frame": "0.0/0",
					"params": "1.25,3,0",
					"proc id": "54",
					"target area": "aoe",
					"target type": "party"
				}
			]
		},
		{
			"bc cost": 28,
			"effects": [
				{
					"bb added atk% based on hp": 930,
					"bb added atk% proportional to hp": "remaining",
					"bb base atk%": 200,
					"bb flat atk": 200,
					"effect delay time(ms)/frame": "16.7/1",
					"params": "200,1130,0,200,0,0,0,0",
					"proc id": "47",
					"target area": "aoe",
					"target type": "enemy"
				},
				{
					"bb atk%": 1130,
					"bb flat atk": 200,
					"effect delay time(ms)/frame": "16.7/1",
					"params": "1130,200,0,0,0,0",
					"proc id": "1",
					"target area": "single",
					"target type": "enemy"
				},
				{
					"bb atk% buff": 530,
					"buff turns (72)": 3,
					"effect delay time(ms)/frame": "0.0/0",
					"params": "530,530,530,3,0",
					"proc id": "45",
					"sbb atk% buff": 530,
					"target area": "aoe",
					"target type": "party",
					"ubb atk% buff": 530
				},
				{
					"% converted turns": 3,
					"atk% buff (46)": 110,
					"converted attribute": "recovery",
					"def% buff (47)": 110,
					"effect delay time(ms)/frame": "0.0/0",
					"params": "3,110,110,0,3,0",
					"proc id": "24",
					"target area": "aoe",
					"target type": "party"
				},
				{
					"buff #1": {
						"atk% buff (2)": -60,
						"proc chance%": 40
					},
					"buff #2": {
						"def% buff (4)": -60,
						"proc chance%": 40
					},
					"buff turns": 2,
					"effect delay time(ms)/frame": "0.0/0",
					"element buffed": "all",
					"params": "0,1,-60,40,2,-60,40,2,0",
					"proc id": "9",
					"target area": "aoe",
					"target type": "enemy"
				},
				{
					"buff turns (84)": 3,
					"crit multiplier%": 125,
					"effect delay time(ms)/frame": "0.0/0",
					"params": "1.25,3,0",
					"proc id": "54",
					"target area": "aoe",
					"target type": "party"
				}
			]
		},
		{
			"bc cost": 28,
			"effects": [
				{
					"bb added atk% based on hp": 940,
					"bb added atk% proportional to hp": "remaining",
					"bb base atk%": 200,
					"bb flat atk": 200,
					"effect delay time(ms)/frame": "16.7/1",
					"params": "200,1140,0,200,0,0,0,0",
					"proc id": "47",
					"target area": "aoe",
					"target type": "enemy"
				},
				{
					"bb atk%": 1140,
					"bb flat atk": 200,
					"effect delay time(ms)/frame": "16.7/1",
					"params": "1140,200,0,0,0,0",
					"proc id": "1",
					"target area": "single",
					"target type": "enemy"
				},
				{
					"bb atk% buff": 540,
					"buff turns (72)": 3,
					"effect delay time(ms)/frame": "0.0/0",
					"params": "540,540,540,3,0",
					"proc id": "45",
					"sbb atk% buff": 540,
					"target area": "aoe",
					"target type": "party",
					"ubb atk% buff": 540
				},
				{
					"% converted turns": 3,
					"atk% buff (46)": 110,
					"converted attribute": "recovery",
					"def% buff (47)": 110,
					"effect delay time(ms)/frame": "0.0/0",
					"params": "3,110,110,0,3,0",
					"proc id": "24",
					"target area": "aoe",
					"target type": "party"
				},
				{
					"buff #1": {
						"atk% buff (2)": -60,
						"proc chance%": 40
					},
					"buff #2": {
						"def% buff (4)": -60,
						"proc chance%": 40
					},
					"buff turns": 2,
					"effect delay time(ms)/frame": "0.0/0",
					"element buffed": "all",
					"params": "0,1,-60,40,2,-60,40,2,0",
					"proc id": "9",
					"target area": "aoe",
					"target type": "enemy"
				},
				{
					"buff turns (84)": 3,
					"crit multiplier%": 125,
					"effect delay time(ms)/frame": "0.0/0",
					"params": "1.25,3,0",
					"proc id": "54",
					"target area": "aoe",
					"target type": "party"
				}
			]
		},
		{
			"bc cost": 28,
			"effects": [
				{
					"bb added atk% based on hp": 950,
					"bb added atk% proportional to hp": "remaining",
					"bb base atk%": 200,
					"bb flat atk": 200,
					"effect delay time(ms)/frame": "16.7/1",
					"params": "200,1150,0,200,0,0,0,0",
					"proc id": "47",
					"target area": "aoe",
					"target type": "enemy"
				},
				{
					"bb atk%": 1150,
					"bb flat atk": 200,
					"effect delay time(ms)/frame": "16.7/1",
					"params": "1150,200,0,0,0,0",
					"proc id": "1",
					"target area": "single",
					"target type": "enemy"
				},
				{
					"bb atk% buff": 550,
					"buff turns (72)": 3,
					"effect delay time(ms)/frame": "0.0/0",
					"params": "550,550,550,3,0",
					"proc id": "45",
					"sbb atk% buff": 550,
					"target area": "aoe",
					"target type": "party",
					"ubb atk% buff": 550
				},
				{
					"% converted turns": 3,
					"atk% buff (46)": 110,
					"converted attribute": "recovery",
					"def% buff (47)": 110,
					"effect delay time(ms)/frame": "0.0/0",
					"params": "3,110,110,0,3,0",
					"proc id": "24",
					"target area": "aoe",
					"target type": "party"
				},
				{
					"buff #1": {
						"atk% buff (2)": -60,
						"proc chance%": 40
					},
					"buff #2": {
						"def% buff (4)": -60,
						"proc chance%": 40
					},
					"buff turns": 2,
					"effect delay time(ms)/frame": "0.0/0",
					"element buffed": "all",
					"params": "0,1,-60,40,2,-60,40,2,0",
					"proc id": "9",
					"target area": "aoe",
					"target type": "enemy"
				},
				{
					"buff turns (84)": 3,
					"crit multiplier%": 125,
					"effect delay time(ms)/frame": "0.0/0",
					"params": "1.25,3,0",
					"proc id": "54",
					"target area": "aoe",
					"target type": "party"
				}
			]
		},
		{
			"bc cost": 28,
			"effects": [
				{
					"bb added atk% based on hp": 960,
					"bb added atk% proportional to hp": "remaining",
					"bb base atk%": 200,
					"bb flat atk": 200,
					"effect delay time(ms)/frame": "16.7/1",
					"params": "200,1160,0,200,0,0,0,0",
					"proc id": "47",
					"target area": "aoe",
					"target type": "enemy"
				},
				{
					"bb atk%": 1160,
					"bb flat atk": 200,
					"effect delay time(ms)/frame": "16.7/1",
					"params": "1160,200,0,0,0,0",
					"proc id": "1",
					"target area": "single",
					"target type": "enemy"
				},
				{
					"bb atk% buff": 560,
					"buff turns (72)": 3,
					"effect delay time(ms)/frame": "0.0/0",
					"params": "560,560,560,3,0",
					"proc id": "45",
					"sbb atk% buff": 560,
					"target area": "aoe",
					"target type": "party",
					"ubb atk% buff": 560
				},
				{
					"% converted turns": 3,
					"atk% buff (46)": 110,
					"converted attribute": "recovery",
					"def% buff (47)": 110,
					"effect delay time(ms)/frame": "0.0/0",
					"params": "3,110,110,0,3,0",
					"proc id": "24",
					"target area": "aoe",
					"target type": "party"
				},
				{
					"buff #1": {
						"atk% buff (2)": -60,
						"proc chance%": 40
					},
					"buff #2": {
						"def% buff (4)": -60,
						"proc chance%": 40
					},
					"buff turns": 2,
					"effect delay time(ms)/frame": "0.0/0",
					"element buffed": "all",
					"params": "0,1,-60,40,2,-60,40,2,0",
					"proc id": "9",
					"target area": "aoe",
					"target type": "enemy"
				},
				{
					"buff turns (84)": 3,
					"crit multiplier%": 125,
					"effect delay time(ms)/frame": "0.0/0",
					"params": "1.25,3,0",
					"proc id": "54",
					"target area": "aoe",
					"target type": "party"
				}
			]
		},
		{
			"bc cost": 28,
			"effects": [
				{
					"bb added atk% based on hp": 970,
					"bb added atk% proportional to hp": "remaining",
					"bb base atk%": 200,
					"bb flat atk": 200,
					"effect delay time(ms)/frame": "16.7/1",
					"params": "200,1170,0,200,0,0,0,0",
					"proc id": "47",
					"target area": "aoe",
					"target type": "enemy"
				},
				{
					"bb atk%": 1170,
					"bb flat atk": 200,
					"effect delay time(ms)/frame": "16.7/1",
					"params": "1170,200,0,0,0,0",
					"proc id": "1",
					"target area": "single",
					"target type": "enemy"
				},
				{
					"bb atk% buff": 570,
					"buff turns (72)": 3,
					"effect delay time(ms)/frame": "0.0/0",
					"params": "570,570,570,3,0",
					"proc id": "45",
					"sbb atk% buff": 570,
					"target area": "aoe",
					"target type": "party",
					"ubb atk% buff": 570
				},
				{
					"% converted turns": 3,
					"atk% buff (46)": 110,
					"converted attribute": "recovery",
					"def% buff (47)": 110,
					"effect delay time(ms)/frame": "0.0/0",
					"params": "3,110,110,0,3,0",
					"proc id": "24",
					"target area": "aoe",
					"target type": "party"
				},
				{
					"buff #1": {
						"atk% buff (2)": -60,
						"proc chance%": 40
					},
					"buff #2": {
						"def% buff (4)": -60,
						"proc chance%": 40
					},
					"buff turns": 2,
					"effect delay time(ms)/frame": "0.0/0",
					"element buffed": "all",
					"params": "0,1,-60,40,2,-60,40,2,0",
					"proc id": "9",
					"target area": "aoe",
					"target type": "enemy"
				},
				{
					"buff turns (84)": 3,
					"crit multiplier%": 125,
					"effect delay time(ms)/frame": "0.0/0",
					"params": "1.25,3,0",
					"proc id": "54",
					"target area": "aoe",
					"target type": "party"
				}
			]
		},
		{
			"bc cost": 28,
			"effects": [
				{
					"bb added atk% based on hp": 980,
					"bb added atk% proportional to hp": "remaining",
					"bb base atk%": 200,
					"bb flat atk": 200,
					"effect delay time(ms)/frame": "16.7/1",
					"params": "200,1180,0,200,0,0,0,0",
					"proc id": "47",
					"target area": "aoe",
					"target type": "enemy"
				},
				{
					"bb atk%": 1180,
					"bb flat atk": 200,
					"effect delay time(ms)/frame": "16.7/1",
					"params": "1180,200,0,0,0,0",
					"proc id": "1",
					"target area": "single",
					"target type": "enemy"
				},
				{
					"bb atk% buff": 580,
					"buff turns (72)": 3,
					"effect delay time(ms)/frame": "0.0/0",
					"params": "580,580,580,3,0",
					"proc id": "45",
					"sbb atk% buff": 580,
					"target area": "aoe",
					"target type": "party",
					"ubb atk% buff": 580
				},
				{
					"% converted turns": 3,
					"atk% buff (46)": 110,
					"converted attribute": "recovery",
					"def% buff (47)": 110,
					"effect delay time(ms)/frame": "0.0/0",
					"params": "3,110,110,0,3,0",
					"proc id": "24",
					"target area": "aoe",
					"target type": "party"
				},
				{
					"buff #1": {
						"atk% buff (2)": -60,
						"proc chance%": 40
					},
					"buff #2": {
						"def% buff (4)": -60,
						"proc chance%": 40
					},
					"buff turns": 2,
					"effect delay time(ms)/frame": "0.0/0",
					"element buffed": "all",
					"params": "0,1,-60,40,2,-60,40,2,0",
					"proc id": "9",
					"target area": "aoe",
					"target type": "enemy"
				},
				{
					"buff turns (84)": 3,
					"crit multiplier%": 125,
					"effect delay time(ms)/frame": "0.0/0",
					"params": "1.25,3,0",
					"proc id": "54",
					"target area": "aoe",
					"target type": "party"
				}
			]
		},
		{
			"bc cost": 28,
			"effects": [
				{
					"bb added atk% based on hp": 1000,
					"bb added atk% proportional to hp": "remaining",
					"bb base atk%": 200,
					"bb flat atk": 200,
					"effect delay time(ms)/frame": "16.7/1",
					"params": "200,1200,0,200,0,0,0,0",
					"proc id": "47",
					"target area": "aoe",
					"target type": "enemy"
				},
				{
					"bb atk%": 1200,
					"bb flat atk": 200,
					"effect delay time(ms)/frame": "16.7/1",
					"params": "1200,200,0,0,0,0",
					"proc id": "1",
					"target area": "single",
					"target type": "enemy"
				},
				{
					"bb atk% buff": 600,
					"buff turns (72)": 3,
					"effect delay time(ms)/frame": "0.0/0",
					"params": "600,600,600,3,0",
					"proc id": "45",
					"sbb atk% buff": 600,
					"target area": "aoe",
					"target type": "party",
					"ubb atk% buff": 600
				},
				{
					"% converted turns": 3,
					"atk% buff (46)": 110,
					"converted attribute": "recovery",
					"def% buff (47)": 110,
					"effect delay time(ms)/frame": "0.0/0",
					"params": "3,110,110,0,3,0",
					"proc id": "24",
					"target area": "aoe",
					"target type": "party"
				},
				{
					"buff #1": {
						"atk% buff (2)": -60,
						"proc chance%": 40
					},
					"buff #2": {
						"def% buff (4)": -60,
						"proc chance%": 40
					},
					"buff turns": 2,
					"effect delay time(ms)/frame": "0.0/0",
					"element buffed": "all",
					"params": "0,1,-60,40,2,-60,40,2,0",
					"proc id": "9",
					"target area": "aoe",
					"target type": "enemy"
				},
				{
					"buff turns (84)": 3,
					"crit multiplier%": 125,
					"effect delay time(ms)/frame": "0.0/0",
					"params": "1.25,3,0",
					"proc id": "54",
					"target area": "aoe",
					"target type": "party"
				}
			]
		}
	],
	"name": "Mind Seal: Electrokinesis"
}