{
	"attackInfo": [
		{
			"hits": 5,
			"id": "28",
			"target": "ST"
		}
	],
	"bfmtMetadata": {
		"createdAt": "2015-08-14T00:39:50.000Z",
		"updatedAt": "2016-11-11T05:06:36.000Z"
	},
	"damage frames": [
		{
			"effect delay time(ms)/frame": "0.0/0",
			"frame times": [
				7,
				22,
				41,
				56,
				78
			],
			"hit dmg% distribution": [
				10,
				10,
				10,
				10,
				60
			],
			"hit dmg% distribution (total)": 100,
			"hits": 5,
			"proc id": "28"
		}
	],
	"desc": "None",
	"drop check count": 1,
	"levels": [
		{
			"bc cost": 16,
			"effects": [
				{
					"effect delay time(ms)/frame": "0.0/0",
					"fixed damage": 50000,
					"proc id": "28",
					"target area": "single",
					"target type": "enemy"
				}
			]
		}
	],
	"name": "Grand Hazard"
}