{
	"associated_units": [
		"10937"
	],
	"bfmtMetadata": {
		"createdAt": "2016-10-06T11:19:25.000Z",
		"updatedAt": "2016-10-06T11:19:25.000Z"
	},
	"desc": "状態異常の敵へのダメージを大幅にアップ＆被ダメージ時、確率でＨＰを回復",
	"effects": [
		{
			"atk% buff when enemy has ailment": 100,
			"atk% buff when enemy has curse": true,
			"atk% buff when enemy has injury": true,
			"atk% buff when enemy has paralysis": true,
			"atk% buff when enemy has poison": true,
			"atk% buff when enemy has sick": true,
			"atk% buff when enemy has weaken": true,
			"conditions": [],
			"passive id": "74",
			"passive target": "self"
		},
		{
			"conditions": [],
			"dmg% to hp% when attacked chance%": 25,
			"dmg% to hp% when attacked high": 25,
			"dmg% to hp% when attacked low": 20,
			"passive id": "24",
			"passive target": "self"
		}
	],
	"name": "真理論の革命者",
	"target": "self"
}