{
	"associated_units": [
		"860418:es"
	],
	"bfmtMetadata": {
		"createdAt": "2017-06-14T11:43:33.000Z",
		"updatedAt": "2020-05-27T11:17:30.000Z"
	},
	"desc": "Spark damage restores HP for all allies, 30% all parameters, 0-100% Atk, Def relative to remaining HP, restores HP each turn & 100% Dark elemental damage",
	"effects": [
		{
			"atk% base buff": 0,
			"atk% extra buff based on hp": 100,
			"buff proportional to hp": "remaining",
			"conditions": [],
			"def% base buff": 0,
			"def% extra buff based on hp": 100,
			"params": "0,100,0,100,0,0,0",
			"passive id": "46",
			"passive target": "self"
		},
		{
			"conditions": [],
			"params": "3000,4000,100",
			"passive id": "33",
			"passive target": "self",
			"rec% added (turn heal)": 20,
			"turn heal high": 4000,
			"turn heal low": 3000
		},
		{
			"atk% buff": 30,
			"conditions": [],
			"def% buff": 30,
			"hp% buff": 30,
			"params": "30,30,30,0,30",
			"passive id": "1",
			"passive target": "self",
			"rec% buff": 30
		},
		{
			"conditions": [],
			"dark units do extra elemental weakness dmg": true,
			"elemental weakness multiplier%": 100,
			"params": "6,0,0,0,0,0,1",
			"passive id": "50",
			"passive target": "self"
		},
		{
			"conditions": [],
			"heal on spark high": 600,
			"heal on spark low": 500,
			"heal on spark%": 100,
			"params": "500,600,100",
			"passive id": "101",
			"passive target": "party"
		}
	],
	"id": "860418",
	"name": "Web of Shattered Deceptions",
	"rarity": "1",
	"target": "self"
}