{
	"bfmtMetadata": {
		"createdAt": "2017-10-11T11:13:17.000Z",
		"updatedAt": "2017-10-11T11:13:17.000Z"
	},
	"desc": "50% boost to Atk of Dark types, 50% boost to Spark damage, adds Dark barrier effect to BB/SBB & raises Atk parameter limits to 130000<br>Boosts Atk, Def when BB gauge is over 50%, adds 22 combo powerful Dark attack on Light types effect to SBB & boosts Dark elemental damage for all allies in Guild Raid",
	"effects": [
		{
			"atk% buff": 75,
			"bb gauge above % buff requirement": 50,
			"conditions": [],
			"def% buff": 75,
			"passive id": "30",
			"passive target": "self"
		},
		{
			"conditions": [],
			"passive id": "66",
			"passive target": "self",
			"trigger on sbb": true,
			"triggered effect": [
				{
					"effect delay time(ms)/frame": "0.0/0",
					"target area": "aoe",
					"target type": "enemy",
					"unknown proc id": "97",
					"unknown proc param": "6,1100,100,0,0,0,0"
				}
			]
		},
		{
			"conditions": [],
			"dark units do extra elemental weakness dmg": true,
			"elemental weakness multiplier%": 25,
			"passive id": "50",
			"passive target": "party"
		}
	],
	"id": "8960288",
	"name": "Energy Effusion Calculation",
	"target": "self"
}