{
	"area": "Frontier Hunter",
	"battle_count": 5,
	"bfmtMetadata": {
		"createdAt": "2017-11-15T11:13:03.000Z",
		"updatedAt": "2017-11-15T11:13:03.000Z"
	},
	"clear_bonus": [],
	"continue": true,
	"desc": "You're at the entrance to the mysterious area that appeared beyond the Vortex Gate. The beasts here are somewhat weak, but nevertheless you mustn't be careless.",
	"difficulty": 1,
	"dungeon": {
		"en": "44th Expedition",
		"es": "44th Expedition",
		"id": "44th Expedition",
		"pt": "44th Expedition",
		"th": "44th Expedition",
		"vi": "44th Expedition"
	},
	"energy_use": 0,
	"id": "1001800",
	"karma": 0,
	"land": "Vortex",
	"mimic_info": {},
	"name": "Uncharted Frontier - Entrance 44",
	"xp": 0,
	"zel": 0
}