{
	"area": "800144",
	"assets": {
		"background": "dungeon_battle_8001431.jpg",
		"battleMusic": "bf021_map_wasteland.mp3",
		"bossMusic": "bf032_btl_pinchi.mp3"
	},
	"battle_count": 1,
	"bfmtMetadata": {
		"createdAt": "2019-07-03T10:10:55.000Z",
		"updatedAt": "2019-07-03T10:10:55.000Z"
	},
	"clear_bonus": [],
	"continue": true,
	"desc": "The climax of the battle has arrived! Will you see victory - or will you be gnawed on in the throes of defeat?",
	"difficulty": 2,
	"dungeon": "800145",
	"energy_use": 25,
	"id": "8301422",
	"karma": 10000,
	"land": "Vortex",
	"mimic_info": {},
	"mimic_info_params": "0,0,0:0,0:0",
	"name": "Crazy Gourmet [Daily]",
	"xp": 10000,
	"zel": 10000
}