{
	"area": "800147",
	"assets": {
		"background": "dungeon_battle_80185.jpg",
		"battleMusic": "bf023_map_ruins.mp3",
		"bossMusic": "bf023_map_ruins.mp3"
	},
	"battle_count": 3,
	"bfmtMetadata": {
		"createdAt": "2019-11-06T12:31:24.000Z",
		"updatedAt": "2019-11-07T08:08:35.000Z"
	},
	"clear_bonus": [
		{
			"unknown": {
				"count": "5",
				"params": "5:800103:5:0:0",
				"rewardId": "800103",
				"type": "5"
			}
		}
	],
	"continue": false,
	"desc": "The crackling specters return with a vengeance.",
	"difficulty": 4,
	"dungeon": "800153",
	"energy_use": 10,
	"id": "8301521",
	"karma": 0,
	"land": "Vortex",
	"mimic_info": {},
	"mimic_info_params": "0,0,0:0,0:0",
	"name": "Electric Boogaloo",
	"requires": "8301520",
	"xp": 2000,
	"zel": 0
}