{
	"area": "Queen of the High Skies",
	"battle_count": 7,
	"bfmtMetadata": {
		"createdAt": "2015-08-13T15:42:33.000Z",
		"updatedAt": "2015-08-13T15:42:33.000Z"
	},
	"clear_bonus": [],
	"continue": true,
	"desc": "If death can't stop her, nothing will. As long as there is a ray of light, she'll trace it down, even to Gaia's end.",
	"difficulty": 3,
	"dungeon": "Queen of the High Skies",
	"energy_use": 25,
	"id": "8352000",
	"karma": 0,
	"land": "Vortex",
	"mimic_info": {},
	"name": "The Holy Sky Mech Lv. 2",
	"xp": 1800,
	"zel": 0
}