{
	"associated_units": [
		"710217:ls"
	],
	"bfmtMetadata": {
		"createdAt": "2017-07-14T05:45:40.000Z",
		"updatedAt": "2017-07-14T05:45:40.000Z"
	},
	"desc": "100% boost to Atk, 60% boost to max HP, 130% boost to Spark damage, greatly boosts BB Atk for 2 turns when Spark damage exceeds certain amount & considerably boosts OD gauge fill rate",
	"effects": [
		{
			"atk% buff": 100,
			"hp% buff": 60,
			"params": "100,0,0,0,60",
			"passive id": "1"
		},
		{
			"damage% for spark": 130,
			"params": "130,0,0,0,0,0",
			"passive id": "31"
		},
		{
			"buff": {
				"bb atk% buff": 250,
				"buff turns (72)": "2",
				"sbb atk% buff": 250,
				"ubb atk% buff": 250
			},
			"params": "72,250&250&250,-1,15,2",
			"passive id": "86",
			"spark count buff activation": 15
		},
		{
			"od fill rate%": 25,
			"params": "25",
			"passive id": "70"
		}
	],
	"id": "710217",
	"name": "Noiseless Frenzy"
}