{
	"associated_units": [
		"51336",
		"51337",
		"61286",
		"61287",
		"810338",
		"820837",
		"820838",
		"840438",
		"860258",
		"860628"
	],
	"bfmtMetadata": {
		"createdAt": "2018-05-30T12:34:04.000Z",
		"updatedAt": "2020-03-12T02:40:25.000Z"
	},
	"desc": "60% boost to all parameters of Thunder types, adds high probability of resistance against 1 KO attack, 75% boost to Spark damage, Spark damage slightly boosts BB gauge & fills BB gauge to max when damage dealt has exceeded certain amount",
	"dictionary": {
		"lore": "A replica of the Wyola's original faction mark, the first of which were carried by the founders of the faction and their chosen successors. Only a select few can channel the crackling lightning within--others simply explode the moment they attempt to channel its energy, often in a spectacular display of pyrotechnics."
	},
	"effect": [
		{
			"atk% buff": 60,
			"def% buff": 60,
			"elements buffed": [
				"thunder"
			],
			"hp% buff": 60,
			"passive id": "2",
			"rec% buff": 60
		},
		{
			"angel idol chance% condition": 0,
			"angel idol recover chance% high": 70,
			"angel idol recover chance% low": 70,
			"angel idol recover counts": 1,
			"passive id": "69"
		},
		{
			"damage% for spark": 75,
			"passive id": "31"
		},
		{
			"bc fill on spark high": 3,
			"bc fill on spark low": 2,
			"bc fill on spark%": 100,
			"passive id": "47"
		},
		{
			"damage dealt threshold activation": 50000,
			"increase bb gauge": 0,
			"passive id": "81"
		}
	],
	"id": 819148,
	"max_stack": 1,
	"name": "Wyola's Honor",
	"raid": false,
	"rarity": 7,
	"sell_price": 30000,
	"sphere type": 1,
	"sphere type text": "Status Boost",
	"thumbnail": "sphere_thum_819148.png",
	"type": "sphere",
	"usage": []
}